cojopy/__init__.py
cojopy/cli.py
cojopy/cojopy.py
cojopy-0.1.2.dist-info/LICENSE
cojopy-0.1.2.dist-info/METADATA
cojopy-0.1.2.dist-info/WHEEL
cojopy-0.1.2.dist-info/entry_points.txt
cojopy-0.1.2.dist-info/RECORD
