Metadata-Version: 2.3
Name: cojopy
Version: 0.1.2
Summary: Conditional Analysis with LD Matrix.
License: MIT
Author: Jianhua Wang
Author-email: jianhua.mert@gmail.com
Requires-Python: >=3.9,<3.13
Classifier: Development Status :: 2 - Pre-Alpha
Classifier: Intended Audience :: Developers
Classifier: License :: OSI Approved :: MIT License
Classifier: Natural Language :: English
Classifier: Programming Language :: Python :: 3
Classifier: Programming Language :: Python :: 3.9
Classifier: Programming Language :: Python :: 3.10
Classifier: Programming Language :: Python :: 3.11
Classifier: Programming Language :: Python :: 3.12
Requires-Dist: numpy (>=1.21.2)
Requires-Dist: pandas (>=1.3.3)
Requires-Dist: scipy (>=1.7.3)
Requires-Dist: typer (>=0.7.0,<0.8.0)
Project-URL: Homepage, https://github.com/Jianhua-Wang/cojopy
